LICENSE
MANIFEST.in
README.rst
setup.cfg
setup.py
submitex/__init__.py
submitex/clitools.py
submitex/collectfloats.py
submitex/metadata.py
submitex/removecomments.py
submitex/replacebib.py
submitex/replacefigs.py
submitex/resolveinputs.py
submitex/resolvepipes.py
submitex/tools.py
submitex.egg-info/PKG-INFO
submitex.egg-info/SOURCES.txt
submitex.egg-info/dependency_links.txt
submitex.egg-info/entry_points.txt
submitex.egg-info/not-zip-safe
submitex.egg-info/top_level.txt
submitex/static/Makefile