Metadata-Version: 2.1
Name: submitex
Version: 0.0.1
Summary: Tools and CLIs to make your tex-files submission-ready.
Home-page: https://github.com/benmaier/submitex
Author: Benjamin F. Maier
Author-email: contact@benmaier.org
License: MIT
Project-URL: Documentation, http://submitex.benmaier.org
Project-URL: Contributing Statement, https://github.com/benmaier/submitex/blob/master/CONTRIBUTING.md
Project-URL: Bug Reports, https://github.com/benmaier/submitex/issues
Project-URL: Source, https://github.com/benmaier/submitex/
Project-URL: PyPI, https://pypi.org/project/submitex/
Classifier: License :: OSI Approved :: MIT License
Classifier: Programming Language :: Python :: 3.6
Classifier: Programming Language :: Python :: 3.7
Classifier: Programming Language :: Python :: 3.8
Classifier: Programming Language :: Python :: 3.9
Classifier: Programming Language :: Python :: 3.10
Classifier: Programming Language :: Python :: 3.11
Classifier: Programming Language :: Python :: 3.12
Requires-Python: >=3.6
License-File: LICENSE
